MANIFEST.in
README.rst
requirements.txt
setup.py
pyhttp/__init__.py
pyhttp.egg-info/PKG-INFO
pyhttp.egg-info/SOURCES.txt
pyhttp.egg-info/dependency_links.txt
pyhttp.egg-info/not-zip-safe
pyhttp.egg-info/requires.txt
pyhttp.egg-info/top_level.txt