Metadata-Version: 1.0
Name: pyhttp
Version: 1.0.0
Summary: An object-oriented layer for the HTTP specification. It provides an abstraction for requests, responses, uploaded files, cookies, etc
Home-page: https://github.com/felixcarmona/pyhttp
Author: Felix Carmona
Author-email: mail@felixcarmona.com
License: UNKNOWN
Platform: UNKNOWN
